{"data":{"allMdx":{"nodes":[{"fields":{"slug":"/test-wiki-elem/"},"frontmatter":{"wid":"WID:6c75cd0e-3709-41eb-8b0f-e2cef04a3850","title":"Test wiki elem"}},{"fields":{"slug":"/wiki/tech/containerization/docker"},"frontmatter":{"wid":"WID:20200715221846176","title":"Docker"}},{"fields":{"slug":"/wiki/tech/containerization/portainer"},"frontmatter":{"wid":"WID:20200715221943957","title":"Portainer"}},{"fields":{"slug":"/wiki/tech/devops/azure/deploy-with-bitbucket-pipelines"},"frontmatter":{"wid":"WID:20200714182130065","title":"Deploying Azure webapp with Bitbucket pipelines"}}]}}}